python_runtime_metrics/__init__.py
python_runtime_metrics/main.py
python_runtime_metrics-1.2.1.dist-info/METADATA
python_runtime_metrics-1.2.1.dist-info/WHEEL
python_runtime_metrics-1.2.1.dist-info/top_level.txt
python_runtime_metrics-1.2.1.dist-info/RECORD
