Metadata-Version: 2.1
Name: python-runtime-metrics
Version: 1.2.1
Summary: A Prometheus metrics collector for runtime metrics
Author: medhun
Author-email: medhun@example.com
Requires-Python: >=3.6
Requires-Dist: prometheus-client
